MybatisKuangjiaRumenjiaochengCYuyanBianchengWangFix1/README.md
MybatisKuangjiaRumenjiaochengCYuyanBianchengWangFix1/__init__.py
MybatisKuangjiaRumenjiaochengCYuyanBianchengWangFix1/__main__.py
MybatisKuangjiaRumenjiaochengCYuyanBianchengWangFix1/file.epub
MybatisKuangjiaRumenjiaochengCYuyanBianchengWangFix1/index.html
MybatisKuangjiaRumenjiaochengCYuyanBianchengWangFix1/css/__init__.py
MybatisKuangjiaRumenjiaochengCYuyanBianchengWangFix1/css/annotations.css
MybatisKuangjiaRumenjiaochengCYuyanBianchengWangFix1/css/main.css
MybatisKuangjiaRumenjiaochengCYuyanBianchengWangFix1/css/normalize.css
MybatisKuangjiaRumenjiaochengCYuyanBianchengWangFix1/css/popup.css
MybatisKuangjiaRumenjiaochengCYuyanBianchengWangFix1/font/__init__.py
MybatisKuangjiaRumenjiaochengCYuyanBianchengWangFix1/font/fontello.eot
MybatisKuangjiaRumenjiaochengCYuyanBianchengWangFix1/font/fontello.svg
MybatisKuangjiaRumenjiaochengCYuyanBianchengWangFix1/font/fontello.ttf
MybatisKuangjiaRumenjiaochengCYuyanBianchengWangFix1/font/fontello.woff
MybatisKuangjiaRumenjiaochengCYuyanBianchengWangFix1/img/__init__.py
MybatisKuangjiaRumenjiaochengCYuyanBianchengWangFix1/img/annotator-glyph-sprite.png
MybatisKuangjiaRumenjiaochengCYuyanBianchengWangFix1/img/annotator-icon-sprite.png
MybatisKuangjiaRumenjiaochengCYuyanBianchengWangFix1/img/apple-touch-icon.png
MybatisKuangjiaRumenjiaochengCYuyanBianchengWangFix1/img/cancelfullscreen.png
MybatisKuangjiaRumenjiaochengCYuyanBianchengWangFix1/img/close.png
MybatisKuangjiaRumenjiaochengCYuyanBianchengWangFix1/img/fullscreen.png
MybatisKuangjiaRumenjiaochengCYuyanBianchengWangFix1/img/loader.gif
MybatisKuangjiaRumenjiaochengCYuyanBianchengWangFix1/img/menu-icon.png
MybatisKuangjiaRumenjiaochengCYuyanBianchengWangFix1/img/save.png
MybatisKuangjiaRumenjiaochengCYuyanBianchengWangFix1/img/saved.png
MybatisKuangjiaRumenjiaochengCYuyanBianchengWangFix1/img/settings-s.png
MybatisKuangjiaRumenjiaochengCYuyanBianchengWangFix1/img/settings.png
mybatis_kuangjia_rumenjiaocheng_c_yuyan_biancheng_wang_fix1-2025.3.24.0.dist-info/METADATA
mybatis_kuangjia_rumenjiaocheng_c_yuyan_biancheng_wang_fix1-2025.3.24.0.dist-info/WHEEL
mybatis_kuangjia_rumenjiaocheng_c_yuyan_biancheng_wang_fix1-2025.3.24.0.dist-info/entry_points.txt
mybatis_kuangjia_rumenjiaocheng_c_yuyan_biancheng_wang_fix1-2025.3.24.0.dist-info/top_level.txt
mybatis_kuangjia_rumenjiaocheng_c_yuyan_biancheng_wang_fix1-2025.3.24.0.dist-info/RECORD
